image_recognition_vladdemo/__init__.py
image_recognition_vladdemo/e2e_test.py
image_recognition_vladdemo/facade.py
image_recognition_vladdemo/image.py
image_recognition_vladdemo/integration_test.py
image_recognition_vladdemo/main.py
image_recognition_vladdemo/recognition.py
image_recognition_vladdemo/singleton.py
image_recognition_vladdemo/strategy.py
image_recognition_vladdemo/unit_test.py
image_recognition_vladdemo-1.5.0.dist-info/LICENSE
image_recognition_vladdemo-1.5.0.dist-info/METADATA
image_recognition_vladdemo-1.5.0.dist-info/WHEEL
image_recognition_vladdemo-1.5.0.dist-info/top_level.txt
image_recognition_vladdemo-1.5.0.dist-info/RECORD
