Metadata-Version: 2.1
Name: image-recognition-vladdemo
Version: 1.5.0
Summary: Package about image recognition
Home-page: https://github.com/vladdemo1/image_recognition
Author: vladdemo
Author-email: vladdemo140@gmail.com
Project-URL: Bug Tracker, https://github.com/vladdemo1/image_recognition/issues
Classifier: Programming Language :: Python :: 3
Classifier: License :: OSI Approved :: MIT License
Classifier: Operating System :: OS Independent
Requires-Python: >=3.6
License-File: LICENSE
